MSA_FET/__init__.py
MSA_FET/__main__.py
MSA_FET/dataset.py
MSA_FET/install.py
MSA_FET/mp_logger.py
MSA_FET/single.py
MSA_FET/utils.py
MSA_FET/ASD/ASD.py
MSA_FET/ASD/__init__.py
MSA_FET/ASD/loss.py
MSA_FET/ASD/talkNet.py
MSA_FET/ASD/model/__init__.py
MSA_FET/ASD/model/attention_layer.py
MSA_FET/ASD/model/audio_encoder.py
MSA_FET/ASD/model/talkNet_model.py
MSA_FET/ASD/model/visual_encoder.py
MSA_FET/ASD/model/face_detector/__init__.py
MSA_FET/ASD/model/face_detector/s3fd/__init__.py
MSA_FET/ASD/model/face_detector/s3fd/box_utils.py
MSA_FET/ASD/model/face_detector/s3fd/nets.py
MSA_FET/aligners/__init__.py
MSA_FET/aligners/base_aligner.py
MSA_FET/aligners/wav2vec2.py
MSA_FET/example_configs/aligned.json
MSA_FET/example_configs/bert.json
MSA_FET/example_configs/glove.json
MSA_FET/example_configs/librosa.json
MSA_FET/example_configs/mediapipe.json
MSA_FET/example_configs/openface.json
MSA_FET/example_configs/opensmile.json
MSA_FET/example_configs/roberta.json
MSA_FET/example_configs/wav2vec+holistic.json
MSA_FET/example_configs/wav2vec.json
MSA_FET/extractors/__init__.py
MSA_FET/extractors/baseExtractor.py
MSA_FET/extractors/audio/__init__.py
MSA_FET/extractors/audio/librosa.py
MSA_FET/extractors/audio/opensmile.py
MSA_FET/extractors/audio/wave2vec.py
MSA_FET/extractors/text/__init__.py
MSA_FET/extractors/text/bert.py
MSA_FET/extractors/text/glove.py
MSA_FET/extractors/text/roberta.py
MSA_FET/extractors/video/__init__.py
MSA_FET/extractors/video/mediapipe.py
MSA_FET/extractors/video/openface.py
MSA_FET/extractors/video/vggface.py
MSA_FET/models/__init__.py
MSA_FET/models/senet50_ft_dat.py
MMSA_FET-0.4.1.dist-info/LICENSE
MMSA_FET-0.4.1.dist-info/METADATA
MMSA_FET-0.4.1.dist-info/WHEEL
MMSA_FET-0.4.1.dist-info/top_level.txt
MMSA_FET-0.4.1.dist-info/RECORD
