Metadata-Version: 2.1
Name: MMSA-FET
Version: 0.4.1
Summary: A Tool for extracting multimodal features from videos.
Home-page: https://github.com/thuiar/MMSA_FET
Author: THUIAR
Maintainer: FlameSky
Project-URL: Documentation, https://github.com/thuiar/MMSA-FET/wiki
Project-URL: Tracker, https://github.com/thuiar/MMSA_FET/issues
Keywords: multimodal,sentiment analysis,feature extraction,mosi,mosei
Classifier: Programming Language :: Python :: 3.10
Classifier: Programming Language :: Python :: 3.11
Classifier: License :: OSI Approved :: GNU General Public License v3 or later (GPLv3+)
Classifier: Operating System :: OS Independent
Requires-Python: >=3.10
License-File: LICENSE
Requires-Dist: torch (>=1.9.1)
Requires-Dist: mediapipe (>=0.8.8.1)
Requires-Dist: opencv-contrib-python (>=4.5.4.58)
Requires-Dist: transformers (>=4.4.0)
Requires-Dist: opensmile (>=2.2.0)
Requires-Dist: librosa (>=0.8.1)
Requires-Dist: numpy (>=1.20.3)
Requires-Dist: pandas (>=1.2.5)
Requires-Dist: tqdm (>=4.62.2)
Requires-Dist: gdown (>=4.4.0)
Requires-Dist: scenedetect (>=0.5.6.1)
Requires-Dist: scipy (>=1.7.3)
Requires-Dist: python-speech-features (>=0.6)
Requires-Dist: ctc-segmentation (>=1.7.3)
